counter_wyra/__init__.py
counter_wyra-0.3.dist-info/METADATA
counter_wyra-0.3.dist-info/WHEEL
counter_wyra-0.3.dist-info/licenses/LICENSE
counter_wyra-0.3.dist-info/RECORD
