Metadata-Version: 2.4
Name: counter_wyra
Version: 0.3
Summary: A random Counter thing I made for no reason at all
Project-URL: Homepage, https://github.com/I4LYT/counter-thing
Project-URL: Issues, https://github.com/I4LYT/counter-thing/issues
Author-email: Arnay Kumar <arnayk@wyra.net>
License-Expression: WTFPL
License-File: LICENSE
Classifier: Operating System :: OS Independent
Classifier: Programming Language :: Python :: 3
Requires-Python: >=3.9
